Metadata-Version: 2.1
Name: pynubia
Version: 0.3.1
Summary: A framework for building beautiful shells.
Home-page: https://gitlab.com/tmlaw/python-nubia
License: BSD-3-Clause
Keywords: cli,shell,interactive,framework
Author: Travis Law
Author-email: tmlaw0182@gmail.com
Requires-Python: >=3.9,<4.0
Classifier: Development Status :: 4 - Beta
Classifier: Environment :: Console
Classifier: Intended Audience :: Developers
Classifier: License :: OSI Approved :: BSD License
Classifier: Natural Language :: English
Classifier: Operating System :: OS Independent
Classifier: Programming Language :: Python :: 3
Classifier: Programming Language :: Python :: 3.9
Classifier: Programming Language :: Python :: 3.10
Classifier: Programming Language :: Python :: 3.11
Classifier: Programming Language :: Python :: 3.12
Classifier: Programming Language :: Python :: 3.13
Classifier: Topic :: Software Development :: Libraries :: Python Modules
Requires-Dist: Pygments (>=2.19.1,<3.0.0)
Requires-Dist: jellyfish (>=1.2.0,<2.0.0)
Requires-Dist: prettytable (>=3.16.0,<4.0.0)
Requires-Dist: prompt-toolkit (>=3.0.51,<4.0.0)
Requires-Dist: pyparsing (>=3.2.3,<4.0.0)
Requires-Dist: termcolor (>=3.1.0,<4.0.0)
Requires-Dist: typing-inspect (>=0.9.0,<0.10.0)
Requires-Dist: wcwidth (>=0.2.13,<0.3.0)
Project-URL: Repository, https://gitlab.com/tmlaw/python-nubia
